aws/__init__.py
aws/client.py
aws/conftest.py
aws/autoscaling/__init__.py
aws/autoscaling/resources.py
aws/cloudtrail/__init__.py
aws/cloudtrail/resources.py
aws/cloudtrail/test_cloudtrail_enabled_in_all_regions.py
aws/cloudtrail/test_cloudtrail_log_validation_enabled.py
aws/ec2/__init__.py
aws/ec2/helpers.py
aws/ec2/resources.py
aws/ec2/test_ec2_all_eips_bound.py
aws/ec2/test_ec2_ebs_snapshot_not_too_old.py
aws/ec2/test_ec2_ebs_snapshots_are_private.py
aws/ec2/test_ec2_ebs_volume_attached_to_instance.py
aws/ec2/test_ec2_ebs_volume_encrypted.py
aws/ec2/test_ec2_ebs_volume_not_piops.py
aws/ec2/test_ec2_instance_has_required_tags.py
aws/ec2/test_ec2_instance_on_acceptable_ami.py
aws/ec2/test_ec2_security_group_in_use.py
aws/ec2/test_ec2_security_group_opens_all_ports.py
aws/ec2/test_ec2_security_group_opens_all_ports_to_all.py
aws/ec2/test_ec2_security_group_opens_all_ports_to_self.py
aws/ec2/test_ec2_security_group_opens_specific_ports_to_all.py
aws/ec2/test_ec2_vpc_flow_log_enabled.py
aws/elasticache/__init__.py
aws/elasticache/resources.py
aws/elasticsearch/__init__.py
aws/elasticsearch/resources.py
aws/elasticsearch/test_elasticsearch_domains_have_logging_enabled.py
aws/iam/__init__.py
aws/iam/helpers.py
aws/iam/resources.py
aws/iam/test_iam_access_key_is_old.py
aws/iam/test_iam_admin_user_with_access_keys.py
aws/iam/test_iam_admin_user_without_mfa.py
aws/iam/test_iam_cross_account_admin_roles_require_mfa.py
aws/iam/test_iam_user_is_inactive.py
aws/iam/test_iam_user_without_mfa.py
aws/rds/__init__.py
aws/rds/helpers.py
aws/rds/resources.py
aws/rds/test_rds_db_instance_backup_enabled.py
aws/rds/test_rds_db_instance_encrypted.py
aws/rds/test_rds_db_instance_is_multiaz.py
aws/rds/test_rds_db_instance_is_postgres_with_invalid_certificate.py
aws/rds/test_rds_db_instance_minor_version_updates_enabled.py
aws/rds/test_rds_db_instance_not_publicly_accessible_by_vpc_sg.py
aws/rds/test_rds_db_instance_storage_type_not_piops.py
frost-0.4.7.dist-info/LICENSE
frost-0.4.7.dist-info/METADATA
frost-0.4.7.dist-info/WHEEL
frost-0.4.7.dist-info/entry_points.txt
frost-0.4.7.dist-info/top_level.txt
frost-0.4.7.dist-info/RECORD
