Metadata-Version: 2.1
Name: frost
Version: 0.4.7
Summary: tests for checking that third party services the Firefox Operations Security or foxsec team uses are configured correctly
Home-page: https://github.com/mozilla/frost
Author: Firefox Operations Security Team (foxsec)
Author-email: foxsec+frost@mozilla.com
License: MPL2
Platform: UNKNOWN
Classifier: Natural Language :: English
Classifier: License :: OSI Approved :: Mozilla Public License 2.0 (MPL 2.0)
Classifier: Operating System :: OS Independent
Classifier: Programming Language :: Python :: 3.8
Requires-Python: >=3.8
Requires-Dist: botocore
Requires-Dist: click
Requires-Dist: coverage
Requires-Dist: google-api-python-client
Requires-Dist: oauth2client
Requires-Dist: pre-commit
Requires-Dist: pytest-cov
Requires-Dist: pytest-json
Requires-Dist: pytest-metadata
Requires-Dist: pytest
Requires-Dist: python-dateutil
Requires-Dist: ruamel.yaml
Requires-Dist: wheel
